{
 "wave": "EDGE-CARRY-BACKFILL-W1",
 "generated_utc": "2026-07-05",
 "db": "signal_performance",
 "selection_rule": "per venue: top-N by current notional OI (volume proxy for OI-less venues) with >= $5M/leg liquidity gate, N=100 cap, at backfill time (2026-07-05).",
 "hl_partial": {
  "backfilled": 17,
  "rule": "top-17 by OI (highest-liquidity, most-executable carry)",
  "tail_deferred": "~35 lower-OI perps deferred to forward-accumulation (same path as OKX/GATE seeds); no follow-up wave."
 },
 "survivorship_note": "current-listing biased; forward accumulation cures it.",
 "venues": {
  "ASTER": {
   "n_symbols": 10,
   "rows": 41460,
   "earliest": "2021-08-27",
   "interval_h": 8,
   "symbols": [
    "ANSEM",
    "ASTER",
    "BNB",
    "BTC",
    "DOGE",
    "ETH",
    "HYPE",
    "LAB",
    "SOL",
    "XRP"
   ]
  },
  "BINANCE": {
   "n_symbols": 100,
   "rows": 358733,
   "earliest": "2020-01-01",
   "interval_h": 8,
   "symbols": [
    "1000BONK",
    "1000PEPE",
    "1000SHIB",
    "AAVE",
    "ADA",
    "AERO",
    "AKE",
    "ALLO",
    "ARPA",
    "ARX",
    "ASTER",
    "AVAX",
    "BAS",
    "BASED",
    "BCH",
    "BEAT",
    "BEL",
    "BIRB",
    "BNB",
    "BTC",
    "CAP",
    "CL",
    "CRCL",
    "DEXE",
    "DOGE",
    "DOGS",
    "DOT",
    "EIGEN",
    "ENA",
    "EPIC",
    "ETH",
    "ETHFI",
    "FARTCOIN",
    "FET",
    "FIL",
    "GRAM",
    "GWEI",
    "H",
    "HBAR",
    "HEI",
    "HMSTR",
    "HOT",
    "HYPE",
    "ICP",
    "INJ",
    "JTO",
    "KORU",
    "LAB",
    "LINK",
    "LIT",
    "LTC",
    "M",
    "MAGMA",
    "MEGA",
    "MIRA",
    "MSTR",
    "MU",
    "NEAR",
    "O",
    "OGN",
    "ONDO",
    "PENGU",
    "PUMP",
    "RE",
    "RIF",
    "RPL",
    "SIREN",
    "SKHYNIX",
    "SKYAI",
    "SLX",
    "SNDK",
    "SOL",
    "SOXL",
    "SPCX",
    "STORJ",
    "SUI",
    "SYN",
    "TAC",
    "TAIKO",
    "TAO",
    "THE",
    "TIA",
    "TLM",
    "TRUMP",
    "TRX",
    "UNI",
    "VANRY",
    "VELVET",
    "VVV",
    "WLD",
    "WLFI",
    "XAG",
    "XAU",
    "XLM",
    "XMR",
    "XPL",
    "XRP",
    "ZEC",
    "ZKP",
    "\u5e01\u5b89\u4eba\u751f"
   ]
  },
  "BYBIT": {
   "n_symbols": 100,
   "rows": 297368,
   "earliest": "2021-01-01",
   "interval_h": 8,
   "symbols": [
    "1000BONK",
    "1000PEPE",
    "AAVE",
    "ADA",
    "AERO",
    "ALGO",
    "ALLO",
    "APT",
    "ARB",
    "ASTER",
    "ATOM",
    "AVAX",
    "BCH",
    "BEAT",
    "BNB",
    "BSB",
    "BTC",
    "CC",
    "CL",
    "CRV",
    "DASH",
    "DEXE",
    "DOGE",
    "DOT",
    "DRAM",
    "DYDX",
    "EIGEN",
    "ENA",
    "ETC",
    "ETH",
    "ETHFI",
    "FARTCOIN",
    "FF",
    "FIL",
    "GRAM",
    "GRASS",
    "H",
    "HBAR",
    "HMSTR",
    "HYPE",
    "ICP",
    "INJ",
    "JTO",
    "JUP",
    "KAS",
    "LAB",
    "LDO",
    "LINK",
    "LIT",
    "LTC",
    "M",
    "MAGMA",
    "MNT",
    "MON",
    "MU",
    "NEAR",
    "ONDO",
    "OP",
    "PAXG",
    "PENDLE",
    "PENGU",
    "POL",
    "POPCAT",
    "PUMPFUN",
    "RENDER",
    "SEI",
    "SHIB1000",
    "SKHYNIX",
    "SLX",
    "SNDK",
    "SOL",
    "SOXL",
    "SPCX",
    "SPX",
    "STABLE",
    "STRK",
    "SUI",
    "TAC",
    "TAO",
    "TIA",
    "TRB",
    "TRUMP",
    "TRX",
    "UNI",
    "USDC",
    "VIRTUAL",
    "VVV",
    "WIF",
    "WLD",
    "WLFI",
    "XAG",
    "XAU",
    "XAUT",
    "XLM",
    "XMR",
    "XPL",
    "XRP",
    "ZEC",
    "ZEREBRO",
    "ZRO"
   ]
  },
  "GATE": {
   "n_symbols": 34,
   "rows": 3985,
   "earliest": "2026-06-05",
   "interval_h": 8,
   "symbols": [
    "ADA",
    "ASTER",
    "AVAX",
    "BCH",
    "BNB",
    "BTC",
    "CL",
    "CRCLX",
    "DOGE",
    "EPIC",
    "ETH",
    "FARTCOIN",
    "HMSTR",
    "HYPE",
    "LAB",
    "LINK",
    "LTC",
    "MU",
    "NEAR",
    "PAXG",
    "PEPE",
    "SKHYNIX",
    "SNDK",
    "SOL",
    "SPCX",
    "SUI",
    "TRX",
    "UNI",
    "WLD",
    "XAG",
    "XAU",
    "XAUT",
    "XRP",
    "ZEC"
   ]
  },
  "HL": {
   "n_symbols": 17,
   "rows": 331076,
   "earliest": "2023-05-12",
   "interval_h": 1,
   "symbols": [
    "AAVE",
    "ADA",
    "BTC",
    "ETH",
    "HYPE",
    "LINK",
    "LIT",
    "NEAR",
    "PUMP",
    "SOL",
    "SUI",
    "WLD",
    "XMR",
    "XPL",
    "XRP",
    "ZEC",
    "ZRO"
   ]
  },
  "KUCOIN": {
   "n_symbols": 82,
   "rows": 280771,
   "earliest": "2020-08-01",
   "interval_h": 8,
   "symbols": [
    "AAVE",
    "ADA",
    "ALGO",
    "ALLO",
    "ARB",
    "ARM",
    "ASTER",
    "AVAX",
    "BAS",
    "BCH",
    "BEAT",
    "BNB",
    "BSB",
    "BTC",
    "CL",
    "COAI",
    "CRO",
    "CRV",
    "DASH",
    "DOGE",
    "DOT",
    "DRAM",
    "EIGEN",
    "ENA",
    "ESPORTS",
    "ETH",
    "EVAA",
    "FARTCOIN",
    "FET",
    "FIL",
    "GRAM",
    "GWEI",
    "H",
    "HBAR",
    "HMSTR",
    "HOME",
    "HYPE",
    "ICP",
    "ID",
    "INJ",
    "JELLYJELLY",
    "LAB",
    "LINK",
    "LIT",
    "LTC",
    "MU",
    "NEAR",
    "ONDO",
    "OPEN",
    "PAXG",
    "PENGU",
    "PEPE",
    "PUMP",
    "RAVE",
    "RE",
    "S",
    "SEI",
    "SIREN",
    "SKHYNIX",
    "SLX",
    "SOL",
    "SOXL",
    "SPCX",
    "STG",
    "SUI",
    "TAC",
    "TAO",
    "TIA",
    "TRUMP",
    "TRX",
    "UB",
    "UNI",
    "USELESS",
    "VELVET",
    "WIF",
    "WLD",
    "XAG",
    "XAUT",
    "XLM",
    "XMR",
    "XRP",
    "ZEC"
   ]
  },
  "OKX": {
   "n_symbols": 55,
   "rows": 5475,
   "earliest": "2026-03-16",
   "interval_h": 8,
   "symbols": [
    "AAVE",
    "ADA",
    "ALLO",
    "ASTER",
    "AVAX",
    "BCH",
    "BEAT",
    "BNB",
    "BTC",
    "CL",
    "CRCL",
    "DOGE",
    "DOT",
    "DRAM",
    "ETC",
    "ETH",
    "FIL",
    "GRAM",
    "HYPE",
    "INTC",
    "JTO",
    "LAB",
    "LINK",
    "LIT",
    "LTC",
    "MRVL",
    "MSTR",
    "MU",
    "NEAR",
    "NVDA",
    "OKB",
    "ONDO",
    "PEPE",
    "PUMP",
    "QQQ",
    "SHIB",
    "SKHYNIX",
    "SNDK",
    "SOL",
    "SOXL",
    "SPCX",
    "SUI",
    "TAO",
    "TRUMP",
    "TRX",
    "TSLA",
    "UNI",
    "WLD",
    "WLFI",
    "XAG",
    "XAU",
    "XLM",
    "XPL",
    "XRP",
    "ZEC"
   ]
  }
 }
}